LICENSE
MANIFEST.in
README.rst
setup.py
c_schedules/__init__.py
c_schedules/admin.py
c_schedules/forms.py
c_schedules/models.py
c_schedules/source.py
c_schedules/tests.py
c_schedules/urls.py
c_schedules/views.py
c_schedules/migrations/0001_initial.py
c_schedules/migrations/0002_auto_20180404_1449.py
c_schedules/migrations/0003_auto_20180404_1452.py
c_schedules/migrations/0004_auto_20180404_1452.py
c_schedules/migrations/__init__.py
c_schedules/rest/__init__.py
c_schedules/rest/v1/__init__.py
c_schedules/rest/v1/serializers.py
c_schedules/rest/v1/urls.py
c_schedules/rest/v1/views.py
c_schedules/static/c_schedules/index.js
c_schedules/static/c_schedules/style.css
c_schedules/static/c_schedules/admin/index.js
c_schedules/static/c_schedules/admin/style.css
c_schedules/static/c_schedules/images/background.gif
c_schedules/templates/admin/c_schedules/change_form.html
c_schedules/templates/c_schedules/create.html
c_schedules/templates/c_schedules/detail.html
c_schedules/templates/c_schedules/form_content.html
c_schedules/templates/c_schedules/list.html
c_schedules/templates/c_schedules/sch_base.html
c_schedules/templates/c_schedules/shedules-area.html
c_schedules/templates/c_schedules/update.html
django_cschedules.egg-info/PKG-INFO
django_cschedules.egg-info/SOURCES.txt
django_cschedules.egg-info/dependency_links.txt
django_cschedules.egg-info/requires.txt
django_cschedules.egg-info/top_level.txt