Metadata-Version: 1.1
Name: django-cschedules
Version: 0.0.11
Summary: Very simple calendar schedule
Home-page: http://git.dpsoft.org/puvka/cshedules.git
Author: puvka
Author-email: lendo.fox@gmail.com
License: BSD License
Platform: UNKNOWN
Classifier: Environment :: Web Environment
Classifier: Framework :: Django
Classifier: Intended Audience :: Developers
Classifier: License :: OSI Approved :: BSD License
Classifier: Operating System :: OS Independent
Classifier: Programming Language :: Python
Classifier: Programming Language :: Python :: 3.6
Classifier: Topic :: Internet :: WWW/HTTP
Classifier: Topic :: Internet :: WWW/HTTP :: Dynamic Content
